{
  "Name": "Christopher Morgan",
  "Email": "christoper.m@gmail.com",
  "Phone": "+44 (0)20 7666 8555",
  "Address": "177 Great Portland Street, London W5W 6PQ",
  "Education": [
    {
      "degree": "Bachelor of Science: Computer Information Systems",
      "institution": "Columbia University, NY",
      "year": "2014"
    }
  ],
  "Experience": [
    {
      "job_title": "Web Developer",
      "company": "Luna Web Design, New York",
      "duration": "09/2015 to 05/2019",
      "description": [
        "Cooperate with designers to create clean interfaces and simple, intuitive interactions and experiences.",
        "Develop project concepts and maintain optimal workflow.",
        "Work with senior developer to manage large, complex design projects for corporate clients.",
        "Complete detailed programming and development tasks for front end public and internal websites as well as challenging back-end server code.",
        "Carry out quality assurance tests to discover errors and optimize usability."
      ]
    }
  ],
  "Skills": [
    "Project management",
    "Strong decision maker",
    "Complex problem solver",
    "Creative design",
    "Innovative",
    "Service-focused"
  ],
  "Languages": [
    "Spanish",
    "Chinese",
    "German"
  ],
  "model": "mistral:latest"
}